anyprompt/__init__.py
anyprompt/cli.py
anyprompt/server.py
anyprompt/static/styles.css
anyprompt/templates/index.html
anyprompt-0.2.0.dist-info/LICENSE
anyprompt-0.2.0.dist-info/METADATA
anyprompt-0.2.0.dist-info/WHEEL
anyprompt-0.2.0.dist-info/entry_points.txt
anyprompt-0.2.0.dist-info/top_level.txt
anyprompt-0.2.0.dist-info/RECORD
