Metadata-Version: 2.2
Name: anyprompt
Version: 0.2.0
Summary: Automatically inspect and visualize LLM prompts and responses in your Python projects
Author-email: anyprompt <info@anyprompt.ai>
License: MIT
Project-URL: Homepage, https://github.com/anyprompt/anyprompt
Project-URL: Documentation, https://github.com/anyprompt/anyprompt
Project-URL: Issues, https://github.com/anyprompt/anyprompt/issues
Keywords: llm,prompt,ai,openai,anthropic,debug,visualization
Classifier: Programming Language :: Python :: 3
Classifier: Programming Language :: Python :: 3.7
Classifier: Programming Language :: Python :: 3.8
Classifier: Programming Language :: Python :: 3.9
Classifier: Programming Language :: Python :: 3.10
Classifier: Programming Language :: Python :: 3.11
Classifier: License :: OSI Approved :: MIT License
Classifier: Operating System :: OS Independent
Classifier: Intended Audience :: Developers
Classifier: Topic :: Software Development :: Libraries :: Python Modules
Classifier: Topic :: Scientific/Engineering :: Artificial Intelligence
Requires-Python: >=3.7
License-File: LICENSE
Requires-Dist: fastapi>=0.95.0
Requires-Dist: uvicorn>=0.22.0
Requires-Dist: jinja2>=3.1.2
Provides-Extra: all
Requires-Dist: requests>=2.28.0; extra == "all"
Requires-Dist: httpx>=0.24.0; extra == "all"
Requires-Dist: aiohttp>=3.8.4; extra == "all"
Dynamic: requires-python
